pyGCodeDecode/__init__.py
pyGCodeDecode/abaqus_file_generator.py
pyGCodeDecode/cli.py
pyGCodeDecode/gcode_interpreter.py
pyGCodeDecode/helpers.py
pyGCodeDecode/junction_handling.py
pyGCodeDecode/planner_block.py
pyGCodeDecode/plotter.py
pyGCodeDecode/result.py
pyGCodeDecode/state.py
pyGCodeDecode/state_generator.py
pyGCodeDecode/tools.py
pyGCodeDecode/utils.py
pyGCodeDecode/data/default_printer_presets.yaml
pyGCodeDecode/examples/benchy.py
pyGCodeDecode/examples/brace.py
pyGCodeDecode/examples/data/bee.gcode
pyGCodeDecode/examples/data/benchy.gcode
pyGCodeDecode/examples/data/brace.gcode
pyGCodeDecode/examples/data/cubhelix.gcode
pyGCodeDecode/examples/data/printer_presets.yaml
pyGCodeDecode/examples/data/triangle.gcode
pygcodedecode-1.4.1.dist-info/licenses/LICENSE
tests/__init__.py
tests/test_end_to_end.py
tests/test_gcode_interpreter.py
tests/test_junction_handling.py
tests/test_planner_block.py
tests/test_progress_fix.py
tests/test_result.py
tests/test_state_generator.py
tests/test_vector4d.py
pygcodedecode-1.4.1.dist-info/METADATA
pygcodedecode-1.4.1.dist-info/WHEEL
pygcodedecode-1.4.1.dist-info/entry_points.txt
pygcodedecode-1.4.1.dist-info/top_level.txt
pygcodedecode-1.4.1.dist-info/RECORD
