Metadata-Version: 2.4
Name: pyGCodeDecode
Version: 1.4.1
Summary: Generate time dependent boundary conditions from a .gcode file.
Author-email: FAST-LB at KIT <lt-github@fast.kit.edu>, Jonathan Knirsch <jonathan.knirsch@student.kit.edu>, Felix Frölich <felix.froelich@kit.edu>, Lukas Hof <lukas.hof@kit.edu>
Project-URL: Code, https://github.com/FAST-LB/pyGCodeDecode
Project-URL: Issues, https://github.com/FAST-LB/pyGCodeDecode/issues
Classifier: Development Status :: 4 - Beta
Classifier: Intended Audience :: Science/Research
Classifier: License :: OSI Approved :: MIT License
Classifier: Operating System :: OS Independent
Classifier: Programming Language :: Python
Classifier: Programming Language :: Python :: 3
Classifier: Programming Language :: Python :: 3.9
Classifier: Programming Language :: Python :: 3.10
Classifier: Programming Language :: Python :: 3.11
Classifier: Programming Language :: Python :: 3.12
Classifier: Programming Language :: Python :: 3.13
Classifier: Topic :: Scientific/Engineering
Requires-Python: >=3.9
License-File: LICENSE
Requires-Dist: numpy
Requires-Dist: matplotlib
Requires-Dist: PyYAML
Requires-Dist: pyvista
Provides-Extra: test
Requires-Dist: pytest-cov; extra == "test"
Requires-Dist: pandas; extra == "test"
Provides-Extra: developer
Requires-Dist: flake8; extra == "developer"
Requires-Dist: isort; extra == "developer"
Requires-Dist: black[jupyter]; extra == "developer"
Requires-Dist: flake8-docstrings; extra == "developer"
Requires-Dist: pre-commit; extra == "developer"
Requires-Dist: pytest-cov; extra == "developer"
Provides-Extra: docs
Requires-Dist: mkdocs; extra == "docs"
Requires-Dist: pydoc-markdown; extra == "docs"
Dynamic: license-file
